{
  "id": "sanctorale.religious-orders.000a",
  "scope": "religious-orders",
  "title": {
    "la": "In anniversario electionis Papæ",
    "es": "Aniversario de la elección del Papa",
    "en": "Anniversary of the election of the Pope",
    "pt-BR": "Aniversário da eleição do Papa",
    "it": "ANNIVERSARIO DELL’ELEZIONE DEL PAPA",
    "fr": "À l’anniversaire de l’élection du Pape",
    "de": "Am Jahrestag der Wahl des Papstes"
  },
  "rank": "optional-memorial",
  "rankLocalized": {
    "la": "Memoria ad libitum",
    "es": "Memoria libre",
    "en": "Optional Memorial",
    "pt-BR": "Memória facultativa",
    "it": "Memoria facoltativa",
    "fr": "Mémoire facultative",
    "de": "Nicht gebotener Gedenktag"
  }
}